{
  "race_id": "202404030509",
  "source": "result_final_odds",
  "official_datetime": "2024-08-24T00:00:00+09:00",
  "fetched_at": "2026-07-21T15:48:26.697353+09:00",
  "status": {
    "tansho": "result"
  },
  "odds": {
    "tansho": {
      "5": 1.9,
      "4": 10.8,
      "1": 2.3,
      "16": 63.1,
      "12": 29.9,
      "10": 18.0,
      "6": 227.9,
      "3": 95.9,
      "9": 14.7,
      "15": 370.9,
      "2": 62.8,
      "11": 102.4,
      "14": 265.2,
      "8": 447.7,
      "7": 345.8,
      "13": 459.6
    }
  }
}