{
  "race_id": "202405050412",
  "source": "result_final_odds",
  "official_datetime": "2024-11-10T00:00:00+09:00",
  "fetched_at": "2026-07-21T15:47:23.306430+09:00",
  "status": {
    "tansho": "result"
  },
  "odds": {
    "tansho": {
      "12": 10.6,
      "13": 2.1,
      "4": 8.1,
      "16": 7.0,
      "14": 35.7,
      "8": 43.1,
      "11": 5.2,
      "3": 20.7,
      "6": 105.3,
      "10": 19.5,
      "5": 32.0,
      "15": 52.8,
      "2": 193.8,
      "9": 184.0,
      "7": 111.7,
      "1": 411.5
    }
  }
}