{
  "race_id": "202505020908",
  "source": "result_final_odds",
  "official_datetime": "2025-05-24T00:00:00+09:00",
  "fetched_at": "2026-07-21T15:41:48.994743+09:00",
  "status": {
    "tansho": "result"
  },
  "odds": {
    "tansho": {
      "1": 2.2,
      "10": 10.8,
      "11": 14.1,
      "9": 3.6,
      "7": 57.8,
      "15": 143.3,
      "12": 7.6,
      "8": 27.3,
      "5": 14.4,
      "3": 103.3,
      "4": 79.3,
      "16": 91.4,
      "14": 30.0,
      "2": 36.0,
      "13": 225.5,
      "6": 420.7
    }
  }
}