{
  "race_id": "202503020402",
  "source": "result_final_odds",
  "official_datetime": "2025-07-06T00:00:00+09:00",
  "fetched_at": "2026-07-21T15:42:55.949545+09:00",
  "status": {
    "tansho": "result"
  },
  "odds": {
    "tansho": {
      "11": 5.7,
      "5": 11.3,
      "2": 2.3,
      "13": 3.5,
      "15": 18.5,
      "3": 91.0,
      "8": 29.6,
      "1": 95.8,
      "4": 110.4,
      "14": 8.2,
      "10": 207.0,
      "9": 39.0,
      "12": 101.8,
      "7": 199.3,
      "6": 273.8
    }
  }
}