{
  "race_id": "202508021210",
  "source": "result_final_odds",
  "official_datetime": "2025-06-01T00:00:00+09:00",
  "fetched_at": "2026-07-21T15:39:13.999347+09:00",
  "status": {
    "tansho": "result"
  },
  "odds": {
    "tansho": {
      "14": 11.2,
      "8": 16.9,
      "16": 22.4,
      "12": 8.5,
      "11": 4.1,
      "1": 34.9,
      "15": 31.7,
      "5": 4.6,
      "13": 10.0,
      "7": 45.1,
      "10": 9.6,
      "4": 21.0,
      "2": 123.3,
      "9": 29.2,
      "6": 39.5,
      "3": 11.8
    }
  }
}