{
  "race_id": "202509040412",
  "source": "result_final_odds",
  "official_datetime": "2025-09-14T00:00:00+09:00",
  "fetched_at": "2026-07-21T15:38:19.505529+09:00",
  "status": {
    "tansho": "result"
  },
  "odds": {
    "tansho": {
      "16": 1.8,
      "8": 38.0,
      "3": 27.0,
      "10": 108.4,
      "15": 139.8,
      "5": 3.4,
      "6": 53.5,
      "4": 30.0,
      "9": 98.7,
      "11": 14.5,
      "12": 28.0,
      "14": 30.5,
      "7": 220.1,
      "2": 109.4,
      "13": 117.1,
      "1": 9.3
    }
  }
}