{
  "schema_version": "keiba-log-2.0",
  "model_version": "v1.0",
  "status": "final",
  "race": {
    "race_id": "202303020209",
    "date": "2023-07-02",
    "track": "福島",
    "race_number": 9,
    "race_name": "さくらんぼ特別",
    "grade": null,
    "surface": "ダート",
    "distance": 1150,
    "direction": "右",
    "field_size": 16,
    "class": "２勝クラス",
    "weight_rule": "定量",
    "weather": "晴",
    "going": "稍重",
    "post_time": "14:36"
  },
  "prediction": {
    "predicted_at": "2026-07-21T15:52:07",
    "odds_basis": "中間オッズ",
    "odds_fetched_at": "2023-07-02T00:00:00+09:00",
    "info_sufficiency": 85,
    "analysis_state": "中間オッズ版",
    "stance": "pass",
    "pace": "ハイペース想定",
    "pace_class": "H",
    "bias": "先行有利",
    "front_pressure_index": 0.819,
    "scenario": {
      "main": {
        "prob": 0.45,
        "title": "ハイ・前傾消耗",
        "type_tag": "差し",
        "code": "G",
        "favorites": [
          {
            "number": "11",
            "name": "フレーゲル"
          },
          {
            "number": "3",
            "name": "プリティインピンク"
          },
          {
            "number": "5",
            "name": "タリエシン"
          }
        ]
      },
      "sub": {
        "prob": 0.35,
        "title": "超ハイ・前総崩れ",
        "type_tag": "差し・追込",
        "code": "XG",
        "favorites": [
          {
            "number": "11",
            "name": "フレーゲル"
          },
          {
            "number": "3",
            "name": "プリティインピンク"
          },
          {
            "number": "5",
            "name": "タリエシン"
          }
        ]
      },
      "other": {
        "prob": 0.2,
        "title": "平均・前残り",
        "type_tag": "好位・先行",
        "code": "H",
        "favorites": [
          {
            "number": "4",
            "name": "ハギノオーロ"
          },
          {
            "number": "6",
            "name": "エコロアイ"
          },
          {
            "number": "14",
            "name": "ミレヴィーナス"
          }
        ]
      }
    },
    "confidence_overall": null,
    "baba_detail": {
      "going": "稍",
      "going_weather": "稍（晴）",
      "detail_label": null,
      "clock_trend": null,
      "fitness_type": null,
      "display_text": "馬場 稍（晴）",
      "favorites": [
        {
          "number": "1",
          "name": "スイートカルデア",
          "reason": "同馬場好走8回"
        },
        {
          "number": "2",
          "name": "ニシノラーナ",
          "reason": "同馬場好走2回"
        },
        {
          "number": "3",
          "name": "プリティインピンク",
          "reason": "同馬場好走11回"
        },
        {
          "number": "4",
          "name": "ハギノオーロ",
          "reason": "同馬場好走4回"
        },
        {
          "number": "5",
          "name": "タリエシン",
          "reason": "同馬場好走2回"
        }
      ]
    },
    "front_runners": [
      {
        "number": "4",
        "name": "ハギノオーロ",
        "type": "逃げ",
        "front_rate": 1.6
      },
      {
        "number": "6",
        "name": "エコロアイ",
        "type": "逃げ",
        "front_rate": 1.6
      },
      {
        "number": "14",
        "name": "ミレヴィーナス",
        "type": "逃げ",
        "front_rate": 1.6
      },
      {
        "number": "2",
        "name": "ニシノラーナ",
        "type": "逃げ",
        "front_rate": 1.4
      },
      {
        "number": "1",
        "name": "スイートカルデア",
        "type": "先行(逃げ候補)",
        "front_rate": 1.2000000000000002
      },
      {
        "number": "16",
        "name": "ドンアミティエ",
        "type": "先行(逃げ候補)",
        "front_rate": 1.2000000000000002
      },
      {
        "number": "9",
        "name": "ブルースコード",
        "type": "先行(番手)",
        "front_rate": 1.0
      },
      {
        "number": "10",
        "name": "エナジーロッソ",
        "type": "先行(番手)",
        "front_rate": 1.0
      },
      {
        "number": "13",
        "name": "アルマセクメト",
        "type": "先行(番手)",
        "front_rate": 0.8
      },
      {
        "number": "12",
        "name": "ロードミッドナイト",
        "type": "先行",
        "front_rate": 0.6
      },
      {
        "number": "15",
        "name": "ナサ",
        "type": "先行(番手)",
        "front_rate": 0.6
      }
    ],
    "front_pressure": {
      "index": 0.819,
      "label": "高い",
      "main_nige": [
        "2ニシノラーナ",
        "4ハギノオーロ",
        "6エコロアイ",
        "14ミレヴィーナス"
      ]
    },
    "inner_outer_bias": {
      "label": "内枠やや有利",
      "gates": [
        {
          "gate": 1,
          "ratio": 1.32
        },
        {
          "gate": 2,
          "ratio": 0.67
        },
        {
          "gate": 3,
          "ratio": 1.05
        },
        {
          "gate": 4,
          "ratio": 1.14
        },
        {
          "gate": 5,
          "ratio": 0.81
        },
        {
          "gate": 6,
          "ratio": 0.85
        },
        {
          "gate": 7,
          "ratio": 0.83
        },
        {
          "gate": 8,
          "ratio": 1.33
        }
      ]
    },
    "leg_bias": [
      {
        "style": "逃げ",
        "win_rate": "33%",
        "rentai_rate": "54%",
        "fukusho_rate": "65%",
        "runs": 95,
        "judgment": "有利"
      },
      {
        "style": "先行",
        "win_rate": "14%",
        "rentai_rate": "30%",
        "fukusho_rate": "46%",
        "runs": 313,
        "judgment": "有利"
      },
      {
        "style": "差し",
        "win_rate": "2%",
        "rentai_rate": "6%",
        "fukusho_rate": "11%",
        "runs": 509,
        "judgment": "不利"
      },
      {
        "style": "追込",
        "win_rate": "0%",
        "rentai_rate": "1%",
        "fukusho_rate": "3%",
        "runs": 542,
        "judgment": "不利"
      }
    ]
  },
  "horses": [
    {
      "number": 1,
      "name": "スイートカルデア",
      "gate": 1,
      "sex_age": "牝5",
      "weight_carried": 56.0,
      "jockey": "木幡巧",
      "sire": "リアルインパクト",
      "running_style": "逃",
      "scratched": false,
      "scores": {
        "s1": 7,
        "s2": 6,
        "s34": 8,
        "s5": 6,
        "s6": 6,
        "s7": 4,
        "s8": 4
      },
      "total": 64.0,
      "rank": 10,
      "estimated_prob": 0.021091,
      "fair_odds": 47.4,
      "odds": 47.6,
      "popularity": 9,
      "ev": 0.0,
      "ability_mark": null,
      "bet_mark": null,
      "landmine_reason": null,
      "finish": 16,
      "finish_text": null,
      "final_odds": 47.6,
      "last_3f": 38.3,
      "passing": "4-5",
      "role": null,
      "grade": "C+",
      "factors": [
        {
          "dim": "s1",
          "label": "①近走",
          "score": 7,
          "weight": 25,
          "items": [
            {
              "sign": "+",
              "label": "追い上げ実績あり"
            }
          ]
        },
        {
          "dim": "s2",
          "label": "②展開",
          "score": 6,
          "weight": 20,
          "items": [
            {
              "sign": "+",
              "label": "好走時の脚: 末脚型"
            },
            {
              "sign": "-",
              "label": "位置取り分散大(σ=0.30)"
            },
            {
              "sign": "-",
              "label": "先行〜後方まで極端にばらつき"
            },
            {
              "sign": "+",
              "label": "逃げ・先行型（逃げ候補）"
            }
          ]
        },
        {
          "dim": "s34",
          "label": "③④条件適性",
          "score": 8,
          "weight": 20,
          "items": [
            {
              "sign": "+",
              "label": "コース・距離: match"
            },
            {
              "sign": "+",
              "label": "馬場: 同馬場好走8回"
            }
          ]
        },
        {
          "dim": "s5",
          "label": "⑤調教",
          "score": 6,
          "weight": 5,
          "items": [
            {
              "sign": "+",
              "label": "調教: 好気合(+0.3)"
            },
            {
              "sign": "+",
              "label": "馬体重: 好走帯477kg付近"
            }
          ]
        },
        {
          "dim": "s6",
          "label": "⑥枠斤騎",
          "score": 6,
          "weight": 15,
          "items": [
            {
              "sign": "+",
              "label": "枠順: 1枠 大幅有利(勝8%複24%/159走)"
            },
            {
              "sign": "-",
              "label": "斤量: +4.0kg / 過去最大55.0kg超"
            },
            {
              "sign": "+",
              "label": "騎手: コース ratio1.08(勝9%複21%/32走)"
            }
          ]
        },
        {
          "dim": "s7",
          "label": "⑦血統",
          "score": 4,
          "weight": 5,
          "items": [
            {
              "sign": "-",
              "label": "複勝率13.6%(縮小後,基準21.8%,9走)"
            }
          ]
        },
        {
          "dim": "s8",
          "label": "⑧ローテ",
          "score": 4,
          "weight": 10,
          "items": [
            {
              "sign": "-",
              "label": "間隔 中39週"
            }
          ]
        }
      ]
    },
    {
      "number": 2,
      "name": "ニシノラーナ",
      "gate": 1,
      "sex_age": "牝4",
      "weight_carried": 56.0,
      "jockey": "杉原",
      "sire": "ザファクター",
      "running_style": "先",
      "scratched": false,
      "scores": {
        "s1": 5,
        "s2": 6,
        "s34": 9,
        "s5": 6,
        "s6": 5,
        "s7": 8,
        "s8": 6
      },
      "total": 62.4,
      "rank": 13,
      "estimated_prob": 0.020432,
      "fair_odds": 48.9,
      "odds": 40.6,
      "popularity": 8,
      "ev": -0.17,
      "ability_mark": null,
      "bet_mark": null,
      "landmine_reason": null,
      "finish": 8,
      "finish_text": null,
      "final_odds": 40.6,
      "last_3f": 37.3,
      "passing": "4-5",
      "role": null,
      "grade": "C",
      "factors": [
        {
          "dim": "s1",
          "label": "①近走",
          "score": 5,
          "weight": 25,
          "items": [
            {
              "sign": "-",
              "label": "格下でのみ好走"
            },
            {
              "sign": "-",
              "label": "直近で内容悪化"
            }
          ]
        },
        {
          "dim": "s2",
          "label": "②展開",
          "score": 6,
          "weight": 20,
          "items": [
            {
              "sign": "+",
              "label": "好走時の脚: 粘込型"
            },
            {
              "sign": "+",
              "label": "逃げ型（主逃げ候補）"
            }
          ]
        },
        {
          "dim": "s34",
          "label": "③④条件適性",
          "score": 9,
          "weight": 20,
          "items": [
            {
              "sign": "+",
              "label": "コース・距離: match"
            },
            {
              "sign": "+",
              "label": "馬場: 同馬場好走2回"
            }
          ]
        },
        {
          "dim": "s5",
          "label": "⑤調教",
          "score": 6,
          "weight": 5,
          "items": [
            {
              "sign": "-",
              "label": "調教: rankC(-0.6)"
            },
            {
              "sign": "+",
              "label": "馬体重: 好走帯484kg付近"
            }
          ]
        },
        {
          "dim": "s6",
          "label": "⑥枠斤騎",
          "score": 5,
          "weight": 15,
          "items": [
            {
              "sign": "+",
              "label": "枠順: 1枠 大幅有利(勝8%複24%/159走)"
            },
            {
              "sign": "-",
              "label": "騎手: コース ratio0.06(勝0%複4%/23走)"
            }
          ]
        },
        {
          "dim": "s7",
          "label": "⑦血統",
          "score": 8,
          "weight": 5,
          "items": [
            {
              "sign": "+",
              "label": "複勝率29.9%(縮小後,基準21.8%,16走)"
            }
          ]
        },
        {
          "dim": "s8",
          "label": "⑧ローテ",
          "score": 6,
          "weight": 10,
          "items": [
            {
              "sign": "+",
              "label": "リスクなし"
            }
          ]
        }
      ]
    },
    {
      "number": 3,
      "name": "プリティインピンク",
      "gate": 2,
      "sex_age": "牝5",
      "weight_carried": 56.0,
      "jockey": "原",
      "sire": "キンシャサノキセキ",
      "running_style": "差",
      "scratched": false,
      "scores": {
        "s1": 7,
        "s2": 8,
        "s34": 9,
        "s5": 6,
        "s6": 5,
        "s7": 4,
        "s8": 6
      },
      "total": 67.0,
      "rank": 5,
      "estimated_prob": 0.026788,
      "fair_odds": 37.3,
      "odds": 59.0,
      "popularity": 10,
      "ev": 0.58,
      "ability_mark": "△",
      "bet_mark": null,
      "landmine_reason": null,
      "finish": 10,
      "finish_text": null,
      "final_odds": 59.0,
      "last_3f": 36.5,
      "passing": "10-9",
      "role": null,
      "grade": "B",
      "factors": [
        {
          "dim": "s1",
          "label": "①近走",
          "score": 7,
          "weight": 25,
          "items": [
            {
              "sign": "+",
              "label": "追い上げ実績あり"
            },
            {
              "sign": "-",
              "label": "直近で内容悪化"
            }
          ]
        },
        {
          "dim": "s2",
          "label": "②展開",
          "score": 8,
          "weight": 20,
          "items": [
            {
              "sign": "+",
              "label": "好走時の脚: 末脚型"
            },
            {
              "sign": "+",
              "label": "差し型（その他）"
            }
          ]
        },
        {
          "dim": "s34",
          "label": "③④条件適性",
          "score": 9,
          "weight": 20,
          "items": [
            {
              "sign": "+",
              "label": "コース・距離: match"
            },
            {
              "sign": "+",
              "label": "馬場: 同馬場好走11回"
            }
          ]
        },
        {
          "dim": "s5",
          "label": "⑤調教",
          "score": 6,
          "weight": 5,
          "items": [
            {
              "sign": "-",
              "label": "調教: rankC(-0.6)"
            },
            {
              "sign": "+",
              "label": "馬体重: 好走帯435kg付近"
            }
          ]
        },
        {
          "dim": "s6",
          "label": "⑥枠斤騎",
          "score": 5,
          "weight": 15,
          "items": [
            {
              "sign": "-",
              "label": "枠順: 2枠 大幅不利(勝4%複13%/163走)"
            },
            {
              "sign": "+",
              "label": "斤量: 同斤量以上で好走歴"
            },
            {
              "sign": "-",
              "label": "騎手: コース ratio0.48(勝2%複12%/40走) / コンビ2走好走1回"
            }
          ]
        },
        {
          "dim": "s7",
          "label": "⑦血統",
          "score": 4,
          "weight": 5,
          "items": [
            {
              "sign": "-",
              "label": "複勝率12.8%(縮小後,基準21.1%,41走)"
            }
          ]
        },
        {
          "dim": "s8",
          "label": "⑧ローテ",
          "score": 6,
          "weight": 10,
          "items": [
            {
              "sign": "-",
              "label": "間隔 中11週"
            }
          ]
        }
      ]
    },
    {
      "number": 4,
      "name": "ハギノオーロ",
      "gate": 2,
      "sex_age": "牝6",
      "weight_carried": 56.0,
      "jockey": "西村淳",
      "sire": "キンシャサノキセキ",
      "running_style": "逃",
      "scratched": false,
      "scores": {
        "s1": 6,
        "s2": 6,
        "s34": 8,
        "s5": 6,
        "s6": 6,
        "s7": 4,
        "s8": 6
      },
      "total": 63.1,
      "rank": 12,
      "estimated_prob": 0.025421,
      "fair_odds": 39.3,
      "odds": 31.4,
      "popularity": 7,
      "ev": -0.2,
      "ability_mark": null,
      "bet_mark": null,
      "landmine_reason": null,
      "finish": 12,
      "finish_text": null,
      "final_odds": 31.4,
      "last_3f": 37.9,
      "passing": "3-3",
      "role": null,
      "grade": "C+",
      "factors": [
        {
          "dim": "s1",
          "label": "①近走",
          "score": 6,
          "weight": 25,
          "items": [
            {
              "sign": "-",
              "label": "直近で内容悪化"
            }
          ]
        },
        {
          "dim": "s2",
          "label": "②展開",
          "score": 6,
          "weight": 20,
          "items": [
            {
              "sign": "+",
              "label": "好走時の脚: 粘込型"
            },
            {
              "sign": "+",
              "label": "逃げ型（主逃げ候補）"
            }
          ]
        },
        {
          "dim": "s34",
          "label": "③④条件適性",
          "score": 8,
          "weight": 20,
          "items": [
            {
              "sign": "+",
              "label": "コース・距離: match"
            },
            {
              "sign": "+",
              "label": "馬場: 同馬場好走4回"
            }
          ]
        },
        {
          "dim": "s5",
          "label": "⑤調教",
          "score": 6,
          "weight": 5,
          "items": [
            {
              "sign": "+",
              "label": "調教: キビキビ(+0.5)"
            },
            {
              "sign": "-",
              "label": "馬体重: 好走帯522kgから12kg乖離"
            }
          ]
        },
        {
          "dim": "s6",
          "label": "⑥枠斤騎",
          "score": 6,
          "weight": 15,
          "items": [
            {
              "sign": "-",
              "label": "枠順: 2枠 大幅不利(勝4%複13%/163走)"
            },
            {
              "sign": "+",
              "label": "斤量: 同斤量以上で好走歴"
            }
          ]
        },
        {
          "dim": "s7",
          "label": "⑦血統",
          "score": 4,
          "weight": 5,
          "items": [
            {
              "sign": "-",
              "label": "複勝率12.8%(縮小後,基準21.1%,41走)"
            }
          ]
        },
        {
          "dim": "s8",
          "label": "⑧ローテ",
          "score": 6,
          "weight": 10,
          "items": [
            {
              "sign": "-",
              "label": "間隔 中11週"
            }
          ]
        }
      ]
    },
    {
      "number": 5,
      "name": "タリエシン",
      "gate": 3,
      "sex_age": "牡3",
      "weight_carried": 55.0,
      "jockey": "Ｍデム",
      "sire": "キンシャサノキセキ",
      "running_style": "差",
      "scratched": false,
      "scores": {
        "s1": 8,
        "s2": 8,
        "s34": 8,
        "s5": 6,
        "s6": 6,
        "s7": 4,
        "s8": 6
      },
      "total": 71.2,
      "rank": 2,
      "estimated_prob": 0.133131,
      "fair_odds": 7.5,
      "odds": 5.9,
      "popularity": 3,
      "ev": -0.21,
      "ability_mark": "○",
      "bet_mark": null,
      "landmine_reason": null,
      "finish": 14,
      "finish_text": null,
      "final_odds": 5.9,
      "last_3f": 36.3,
      "passing": "14-13",
      "role": null,
      "grade": "B+",
      "factors": [
        {
          "dim": "s1",
          "label": "①近走",
          "score": 8,
          "weight": 25,
          "items": [
            {
              "sign": "+",
              "label": "直近で内容改善"
            },
            {
              "sign": "+",
              "label": "追い上げ実績あり"
            },
            {
              "sign": "-",
              "label": "格下でのみ好走"
            }
          ]
        },
        {
          "dim": "s2",
          "label": "②展開",
          "score": 8,
          "weight": 20,
          "items": [
            {
              "sign": "+",
              "label": "好走時の脚: 末脚型"
            },
            {
              "sign": "+",
              "label": "差し型（その他）"
            }
          ]
        },
        {
          "dim": "s34",
          "label": "③④条件適性",
          "score": 8,
          "weight": 20,
          "items": [
            {
              "sign": "+",
              "label": "コース・距離: match"
            },
            {
              "sign": "+",
              "label": "馬場: 同馬場好走2回"
            }
          ]
        },
        {
          "dim": "s5",
          "label": "⑤調教",
          "score": 6,
          "weight": 5,
          "items": [
            {
              "sign": "+",
              "label": "調教: 動き良化(+0.3)"
            },
            {
              "sign": "+",
              "label": "馬体重: 好走帯434kg付近"
            }
          ]
        },
        {
          "dim": "s6",
          "label": "⑥枠斤騎",
          "score": 6,
          "weight": 15,
          "items": [
            {
              "sign": "+",
              "label": "枠順: 3枠 標準(勝7%複20%/205走)"
            },
            {
              "sign": "+",
              "label": "斤量: 同斤量以上で好走歴"
            }
          ]
        },
        {
          "dim": "s7",
          "label": "⑦血統",
          "score": 4,
          "weight": 5,
          "items": [
            {
              "sign": "-",
              "label": "複勝率12.8%(縮小後,基準21.1%,41走)"
            }
          ]
        },
        {
          "dim": "s8",
          "label": "⑧ローテ",
          "score": 6,
          "weight": 10,
          "items": [
            {
              "sign": "+",
              "label": "リスクなし"
            }
          ]
        }
      ]
    },
    {
      "number": 6,
      "name": "エコロアイ",
      "gate": 3,
      "sex_age": "牝3",
      "weight_carried": 53.0,
      "jockey": "幸",
      "sire": "Shackleford",
      "running_style": "逃",
      "scratched": false,
      "scores": {
        "s1": 5,
        "s2": 6,
        "s34": 8,
        "s5": 6,
        "s6": 6,
        "s7": 6,
        "s8": 6
      },
      "total": 60.8,
      "rank": 14,
      "estimated_prob": 0.041462,
      "fair_odds": 24.1,
      "odds": 15.0,
      "popularity": 4,
      "ev": -0.38,
      "ability_mark": null,
      "bet_mark": "地雷",
      "landmine_reason": "単勝15.0倍(4番人気)だが推定勝率4.1%・単勝EV-38%",
      "finish": 2,
      "finish_text": null,
      "final_odds": 15.0,
      "last_3f": 37.1,
      "passing": "1-1",
      "role": null,
      "grade": "C",
      "factors": [
        {
          "dim": "s1",
          "label": "①近走",
          "score": 5,
          "weight": 25,
          "items": [
            {
              "sign": "-",
              "label": "同級で安定して凡走"
            },
            {
              "sign": "-",
              "label": "直近で内容悪化"
            }
          ]
        },
        {
          "dim": "s2",
          "label": "②展開",
          "score": 6,
          "weight": 20,
          "items": [
            {
              "sign": "+",
              "label": "好走時の脚: 粘込型"
            },
            {
              "sign": "+",
              "label": "逃げ型（主逃げ候補）"
            }
          ]
        },
        {
          "dim": "s34",
          "label": "③④条件適性",
          "score": 8,
          "weight": 20,
          "items": [
            {
              "sign": "+",
              "label": "コース・距離: match"
            },
            {
              "sign": "+",
              "label": "馬場: 同馬場好走1回"
            }
          ]
        },
        {
          "dim": "s5",
          "label": "⑤調教",
          "score": 6,
          "weight": 5,
          "items": [
            {
              "sign": "+",
              "label": "調教: 前走以上(+0.3)"
            }
          ]
        },
        {
          "dim": "s6",
          "label": "⑥枠斤騎",
          "score": 6,
          "weight": 15,
          "items": [
            {
              "sign": "+",
              "label": "枠順: 3枠 標準(勝7%複20%/205走)"
            },
            {
              "sign": "+",
              "label": "斤量: 同斤量以上で好走歴"
            }
          ]
        },
        {
          "dim": "s7",
          "label": "⑦血統",
          "score": 6,
          "weight": 5,
          "items": []
        },
        {
          "dim": "s8",
          "label": "⑧ローテ",
          "score": 6,
          "weight": 10,
          "items": [
            {
              "sign": "+",
              "label": "リスクなし"
            }
          ]
        }
      ]
    },
    {
      "number": 7,
      "name": "ウメタロウ",
      "gate": 4,
      "sex_age": "牡8",
      "weight_carried": 58.0,
      "jockey": "内田博",
      "sire": "プリサイスエンド",
      "running_style": "差",
      "scratched": false,
      "scores": {
        "s1": 5,
        "s2": 8,
        "s34": 9,
        "s5": 6,
        "s6": 6,
        "s7": 6,
        "s8": 5
      },
      "total": 66.2,
      "rank": 6,
      "estimated_prob": 0.016885,
      "fair_odds": 59.2,
      "odds": 281.3,
      "popularity": 16,
      "ev": 3.75,
      "ability_mark": null,
      "bet_mark": null,
      "landmine_reason": null,
      "finish": 9,
      "finish_text": null,
      "final_odds": 281.3,
      "last_3f": 36.9,
      "passing": "7-8",
      "role": null,
      "grade": "B",
      "factors": [
        {
          "dim": "s1",
          "label": "①近走",
          "score": 5,
          "weight": 25,
          "items": [
            {
              "sign": "+",
              "label": "追い上げ実績あり"
            },
            {
              "sign": "-",
              "label": "同級で安定して凡走"
            }
          ]
        },
        {
          "dim": "s2",
          "label": "②展開",
          "score": 8,
          "weight": 20,
          "items": [
            {
              "sign": "+",
              "label": "好位型（その他）"
            }
          ]
        },
        {
          "dim": "s34",
          "label": "③④条件適性",
          "score": 9,
          "weight": 20,
          "items": [
            {
              "sign": "+",
              "label": "コース・距離: match"
            },
            {
              "sign": "+",
              "label": "馬場: 同馬場好走2回"
            }
          ]
        },
        {
          "dim": "s5",
          "label": "⑤調教",
          "score": 6,
          "weight": 5,
          "items": [
            {
              "sign": "-",
              "label": "調教: rankC(-0.6) / 目立たず(-0.3)"
            }
          ]
        },
        {
          "dim": "s6",
          "label": "⑥枠斤騎",
          "score": 6,
          "weight": 15,
          "items": [
            {
              "sign": "+",
              "label": "枠順: 4枠 有利(勝7%複22%/209走)"
            }
          ]
        },
        {
          "dim": "s7",
          "label": "⑦血統",
          "score": 6,
          "weight": 5,
          "items": []
        },
        {
          "dim": "s8",
          "label": "⑧ローテ",
          "score": 5,
          "weight": 10,
          "items": [
            {
              "sign": "-",
              "label": "間隔 中11週"
            }
          ]
        }
      ]
    },
    {
      "number": 8,
      "name": "アイスマン",
      "gate": 4,
      "sex_age": "牡5",
      "weight_carried": 58.0,
      "jockey": "丸山",
      "sire": "スウェプトオーヴァーボード",
      "running_style": "差",
      "scratched": false,
      "scores": {
        "s1": 6,
        "s2": 8,
        "s34": 8,
        "s5": 5,
        "s6": 5,
        "s7": 6,
        "s8": 6
      },
      "total": 64.7,
      "rank": 9,
      "estimated_prob": 0.016365,
      "fair_odds": 61.1,
      "odds": 103.1,
      "popularity": 13,
      "ev": 0.69,
      "ability_mark": null,
      "bet_mark": null,
      "landmine_reason": null,
      "finish": 6,
      "finish_text": null,
      "final_odds": 103.1,
      "last_3f": 35.9,
      "passing": "12-12",
      "role": null,
      "grade": "C+",
      "factors": [
        {
          "dim": "s1",
          "label": "①近走",
          "score": 6,
          "weight": 25,
          "items": [
            {
              "sign": "+",
              "label": "追い上げ実績あり"
            },
            {
              "sign": "-",
              "label": "格下でのみ好走"
            }
          ]
        },
        {
          "dim": "s2",
          "label": "②展開",
          "score": 8,
          "weight": 20,
          "items": [
            {
              "sign": "-",
              "label": "先行〜後方まで極端にばらつき"
            },
            {
              "sign": "+",
              "label": "好位型（好位勢）"
            }
          ]
        },
        {
          "dim": "s34",
          "label": "③④条件適性",
          "score": 8,
          "weight": 20,
          "items": [
            {
              "sign": "+",
              "label": "コース・距離: match"
            },
            {
              "sign": "+",
              "label": "馬場: 同馬場好走7回"
            }
          ]
        },
        {
          "dim": "s5",
          "label": "⑤調教",
          "score": 5,
          "weight": 5,
          "items": [
            {
              "sign": "-",
              "label": "調教: rankD(-1.0) / いま一息(-0.5)"
            }
          ]
        },
        {
          "dim": "s6",
          "label": "⑥枠斤騎",
          "score": 5,
          "weight": 15,
          "items": [
            {
              "sign": "+",
              "label": "枠順: 4枠 有利(勝7%複22%/209走)"
            },
            {
              "sign": "-",
              "label": "騎手: コース ratio0.37(勝0%複15%/20走) / コンビ好走あり"
            }
          ]
        },
        {
          "dim": "s7",
          "label": "⑦血統",
          "score": 6,
          "weight": 5,
          "items": []
        },
        {
          "dim": "s8",
          "label": "⑧ローテ",
          "score": 6,
          "weight": 10,
          "items": [
            {
              "sign": "-",
              "label": "間隔 中2週"
            }
          ]
        }
      ]
    },
    {
      "number": 9,
      "name": "ブルースコード",
      "gate": 5,
      "sex_age": "牡5",
      "weight_carried": 58.0,
      "jockey": "永野",
      "sire": "ミッキーアイル",
      "running_style": "先",
      "scratched": false,
      "scores": {
        "s1": 5,
        "s2": 6,
        "s34": 8,
        "s5": 6,
        "s6": 5,
        "s7": 5,
        "s8": 6
      },
      "total": 60.0,
      "rank": 15,
      "estimated_prob": 0.010175,
      "fair_odds": 98.3,
      "odds": 93.3,
      "popularity": 12,
      "ev": -0.05,
      "ability_mark": null,
      "bet_mark": null,
      "landmine_reason": null,
      "finish": 7,
      "finish_text": null,
      "final_odds": 93.3,
      "last_3f": 37.3,
      "passing": "4-3",
      "role": null,
      "grade": "C",
      "factors": [
        {
          "dim": "s1",
          "label": "①近走",
          "score": 5,
          "weight": 25,
          "items": [
            {
              "sign": "-",
              "label": "直近で内容悪化"
            }
          ]
        },
        {
          "dim": "s2",
          "label": "②展開",
          "score": 6,
          "weight": 20,
          "items": [
            {
              "sign": "+",
              "label": "好走時の脚: 粘込型"
            },
            {
              "sign": "+",
              "label": "逃げ・先行型（逃げ候補）"
            }
          ]
        },
        {
          "dim": "s34",
          "label": "③④条件適性",
          "score": 8,
          "weight": 20,
          "items": [
            {
              "sign": "+",
              "label": "コース・距離: match"
            },
            {
              "sign": "+",
              "label": "馬場: 同馬場好走4回"
            }
          ]
        },
        {
          "dim": "s5",
          "label": "⑤調教",
          "score": 6,
          "weight": 5,
          "items": [
            {
              "sign": "-",
              "label": "調教: rankC(-0.6) / 多少良化(+0.3)"
            },
            {
              "sign": "+",
              "label": "馬体重: 好走帯493kg付近"
            }
          ]
        },
        {
          "dim": "s6",
          "label": "⑥枠斤騎",
          "score": 5,
          "weight": 15,
          "items": [
            {
              "sign": "-",
              "label": "枠順: 5枠 不利(勝5%複17%/213走)"
            },
            {
              "sign": "-",
              "label": "騎手: コース ratio0.58(勝2%複17%/35走) / コンビ3走好走2回"
            }
          ]
        },
        {
          "dim": "s7",
          "label": "⑦血統",
          "score": 5,
          "weight": 5,
          "items": [
            {
              "sign": "-",
              "label": "複勝率15.8%(縮小後,基準21.1%,24走)"
            }
          ]
        },
        {
          "dim": "s8",
          "label": "⑧ローテ",
          "score": 6,
          "weight": 10,
          "items": [
            {
              "sign": "-",
              "label": "間隔 中11週"
            }
          ]
        }
      ]
    },
    {
      "number": 10,
      "name": "エナジーロッソ",
      "gate": 5,
      "sex_age": "牝5",
      "weight_carried": 56.0,
      "jockey": "北村宏",
      "sire": "ホッコータルマエ",
      "running_style": "先",
      "scratched": false,
      "scores": {
        "s1": 4,
        "s2": 6,
        "s34": 8,
        "s5": 6,
        "s6": 6,
        "s7": 5,
        "s8": 6
      },
      "total": 59.1,
      "rank": 16,
      "estimated_prob": 0.010719,
      "fair_odds": 93.3,
      "odds": 76.8,
      "popularity": 11,
      "ev": -0.18,
      "ability_mark": null,
      "bet_mark": null,
      "landmine_reason": null,
      "finish": 5,
      "finish_text": null,
      "final_odds": 76.8,
      "last_3f": 36.2,
      "passing": "10-9",
      "role": null,
      "grade": "D",
      "factors": [
        {
          "dim": "s1",
          "label": "①近走",
          "score": 4,
          "weight": 25,
          "items": [
            {
              "sign": "-",
              "label": "格下でのみ好走"
            },
            {
              "sign": "-",
              "label": "直近で内容悪化"
            }
          ]
        },
        {
          "dim": "s2",
          "label": "②展開",
          "score": 6,
          "weight": 20,
          "items": [
            {
              "sign": "+",
              "label": "好走時の脚: 粘込型"
            },
            {
              "sign": "-",
              "label": "位置取り分散大(σ=0.41)"
            },
            {
              "sign": "-",
              "label": "先行〜後方まで極端にばらつき"
            },
            {
              "sign": "+",
              "label": "逃げ・先行型（逃げ候補）"
            }
          ]
        },
        {
          "dim": "s34",
          "label": "③④条件適性",
          "score": 8,
          "weight": 20,
          "items": [
            {
              "sign": "+",
              "label": "コース・距離: match"
            },
            {
              "sign": "+",
              "label": "馬場: 同馬場好走7回"
            }
          ]
        },
        {
          "dim": "s5",
          "label": "⑤調教",
          "score": 6,
          "weight": 5,
          "items": [
            {
              "sign": "+",
              "label": "調教: 出来は良(+0.5)"
            },
            {
              "sign": "-",
              "label": "馬体重: 前走比-14kg(-2.8%)"
            }
          ]
        },
        {
          "dim": "s6",
          "label": "⑥枠斤騎",
          "score": 6,
          "weight": 15,
          "items": [
            {
              "sign": "-",
              "label": "枠順: 5枠 不利(勝5%複17%/213走)"
            },
            {
              "sign": "+",
              "label": "斤量: 同斤量以上で好走歴"
            }
          ]
        },
        {
          "dim": "s7",
          "label": "⑦血統",
          "score": 5,
          "weight": 5,
          "items": [
            {
              "sign": "-",
              "label": "複勝率18.6%(縮小後,基準21.8%,24走)"
            }
          ]
        },
        {
          "dim": "s8",
          "label": "⑧ローテ",
          "score": 6,
          "weight": 10,
          "items": [
            {
              "sign": "+",
              "label": "リスクなし"
            }
          ]
        }
      ]
    },
    {
      "number": 11,
      "name": "フレーゲル",
      "gate": 6,
      "sex_age": "牡5",
      "weight_carried": 58.0,
      "jockey": "津村",
      "sire": "トゥザワールド",
      "running_style": "追",
      "scratched": false,
      "scores": {
        "s1": 6,
        "s2": 8,
        "s34": 8,
        "s5": 5,
        "s6": 8,
        "s7": 6,
        "s8": 6
      },
      "total": 68.8,
      "rank": 3,
      "estimated_prob": 0.047234,
      "fair_odds": 21.2,
      "odds": 24.7,
      "popularity": 6,
      "ev": 0.17,
      "ability_mark": "▲",
      "bet_mark": null,
      "landmine_reason": null,
      "finish": 15,
      "finish_text": null,
      "final_odds": 24.7,
      "last_3f": 36.4,
      "passing": "14-15",
      "role": null,
      "grade": "B",
      "factors": [
        {
          "dim": "s1",
          "label": "①近走",
          "score": 6,
          "weight": 25,
          "items": [
            {
              "sign": "+",
              "label": "追い上げ実績あり"
            },
            {
              "sign": "-",
              "label": "格下でのみ好走"
            },
            {
              "sign": "-",
              "label": "直近で内容悪化"
            }
          ]
        },
        {
          "dim": "s2",
          "label": "②展開",
          "score": 8,
          "weight": 20,
          "items": [
            {
              "sign": "+",
              "label": "好走時の脚: 末脚型"
            },
            {
              "sign": "+",
              "label": "差し型（その他）"
            }
          ]
        },
        {
          "dim": "s34",
          "label": "③④条件適性",
          "score": 8,
          "weight": 20,
          "items": [
            {
              "sign": "+",
              "label": "コース・距離: match"
            },
            {
              "sign": "+",
              "label": "馬場: 同馬場好走3回"
            }
          ]
        },
        {
          "dim": "s5",
          "label": "⑤調教",
          "score": 5,
          "weight": 5,
          "items": [
            {
              "sign": "-",
              "label": "調教: rankD(-1.0) / 動き平凡(-0.3)"
            },
            {
              "sign": "+",
              "label": "馬体重: 好走帯485kg付近"
            }
          ]
        },
        {
          "dim": "s6",
          "label": "⑥枠斤騎",
          "score": 8,
          "weight": 15,
          "items": [
            {
              "sign": "-",
              "label": "枠順: 6枠 不利(勝5%複17%/218走)"
            },
            {
              "sign": "+",
              "label": "斤量: 同斤量以上で好走歴"
            },
            {
              "sign": "+",
              "label": "騎手: コース ratio1.84(勝17%複30%/23走) / コンビ5走好走2回"
            }
          ]
        },
        {
          "dim": "s7",
          "label": "⑦血統",
          "score": 6,
          "weight": 5,
          "items": [
            {
              "sign": "+",
              "label": "複勝率22.5%(縮小後,基準21.8%,4走)"
            }
          ]
        },
        {
          "dim": "s8",
          "label": "⑧ローテ",
          "score": 6,
          "weight": 10,
          "items": [
            {
              "sign": "-",
              "label": "間隔 中11週"
            }
          ]
        }
      ]
    },
    {
      "number": 12,
      "name": "ロードミッドナイト",
      "gate": 6,
      "sex_age": "牡5",
      "weight_carried": 58.0,
      "jockey": "戸崎圭",
      "sire": "カレンブラックヒル",
      "running_style": "差",
      "scratched": false,
      "scores": {
        "s1": 9,
        "s2": 6,
        "s34": 9,
        "s5": 6,
        "s6": 7,
        "s7": 7,
        "s8": 6
      },
      "total": 75.7,
      "rank": 1,
      "estimated_prob": 0.223962,
      "fair_odds": 4.5,
      "odds": 4.4,
      "popularity": 2,
      "ev": -0.01,
      "ability_mark": "◎",
      "bet_mark": null,
      "landmine_reason": null,
      "finish": 3,
      "finish_text": null,
      "final_odds": 4.4,
      "last_3f": 36.1,
      "passing": "7-7",
      "role": null,
      "grade": "A+",
      "factors": [
        {
          "dim": "s1",
          "label": "①近走",
          "score": 9,
          "weight": 25,
          "items": [
            {
              "sign": "+",
              "label": "同級小差3回以上"
            },
            {
              "sign": "+",
              "label": "直近で内容改善"
            },
            {
              "sign": "+",
              "label": "追い上げ実績あり"
            }
          ]
        },
        {
          "dim": "s2",
          "label": "②展開",
          "score": 6,
          "weight": 20,
          "items": [
            {
              "sign": "+",
              "label": "好走時の脚: 先行押切型"
            },
            {
              "sign": "+",
              "label": "先行型（先行勢）"
            }
          ]
        },
        {
          "dim": "s34",
          "label": "③④条件適性",
          "score": 9,
          "weight": 20,
          "items": [
            {
              "sign": "+",
              "label": "コース・距離: match"
            },
            {
              "sign": "+",
              "label": "馬場: 同馬場好走8回"
            }
          ]
        },
        {
          "dim": "s5",
          "label": "⑤調教",
          "score": 6,
          "weight": 5,
          "items": [
            {
              "sign": "+",
              "label": "調教: 元気一杯(+0.5)"
            },
            {
              "sign": "+",
              "label": "馬体重: 好走帯534kg付近 / 3走で-12kg減少傾向"
            }
          ]
        },
        {
          "dim": "s6",
          "label": "⑥枠斤騎",
          "score": 7,
          "weight": 15,
          "items": [
            {
              "sign": "-",
              "label": "枠順: 6枠 不利(勝5%複17%/218走)"
            },
            {
              "sign": "+",
              "label": "斤量: 同斤量以上で好走歴"
            },
            {
              "sign": "+",
              "label": "騎手: コース ratio2.24(勝14%複50%/34走)"
            }
          ]
        },
        {
          "dim": "s7",
          "label": "⑦血統",
          "score": 7,
          "weight": 5,
          "items": [
            {
              "sign": "+",
              "label": "複勝率25.8%(縮小後,基準21.8%,21走)"
            }
          ]
        },
        {
          "dim": "s8",
          "label": "⑧ローテ",
          "score": 6,
          "weight": 10,
          "items": [
            {
              "sign": "-",
              "label": "使い詰め"
            }
          ]
        }
      ]
    },
    {
      "number": 13,
      "name": "アルマセクメト",
      "gate": 7,
      "sex_age": "牝5",
      "weight_carried": 56.0,
      "jockey": "三浦",
      "sire": "プリサイスエンド",
      "running_style": "先",
      "scratched": false,
      "scores": {
        "s1": 6,
        "s2": 6,
        "s34": 8,
        "s5": 6,
        "s6": 7,
        "s7": 6,
        "s8": 5
      },
      "total": 64.9,
      "rank": 8,
      "estimated_prob": 0.015154,
      "fair_odds": 66.0,
      "odds": 150.3,
      "popularity": 15,
      "ev": 1.28,
      "ability_mark": null,
      "bet_mark": null,
      "landmine_reason": null,
      "finish": 13,
      "finish_text": null,
      "final_odds": 150.3,
      "last_3f": 36.6,
      "passing": "12-15",
      "role": null,
      "grade": "C+",
      "factors": [
        {
          "dim": "s1",
          "label": "①近走",
          "score": 6,
          "weight": 25,
          "items": []
        },
        {
          "dim": "s2",
          "label": "②展開",
          "score": 6,
          "weight": 20,
          "items": [
            {
              "sign": "+",
              "label": "好走時の脚: 粘込型"
            },
            {
              "sign": "-",
              "label": "位置取り分散大(σ=0.32)"
            },
            {
              "sign": "+",
              "label": "逃げ・先行型（逃げ候補）"
            }
          ]
        },
        {
          "dim": "s34",
          "label": "③④条件適性",
          "score": 8,
          "weight": 20,
          "items": [
            {
              "sign": "+",
              "label": "コース・距離: match"
            },
            {
              "sign": "+",
              "label": "馬場: 同馬場好走7回"
            }
          ]
        },
        {
          "dim": "s5",
          "label": "⑤調教",
          "score": 6,
          "weight": 5,
          "items": [
            {
              "sign": "-",
              "label": "調教: rankC(-0.6)"
            },
            {
              "sign": "-",
              "label": "馬体重: 3走で+12kg増加傾向"
            }
          ]
        },
        {
          "dim": "s6",
          "label": "⑥枠斤騎",
          "score": 7,
          "weight": 15,
          "items": [
            {
              "sign": "-",
              "label": "枠順: 7枠 不利(勝5%複16%/219走)"
            },
            {
              "sign": "+",
              "label": "騎手: コース ratio2.18(勝17%複41%/29走)"
            }
          ]
        },
        {
          "dim": "s7",
          "label": "⑦血統",
          "score": 6,
          "weight": 5,
          "items": []
        },
        {
          "dim": "s8",
          "label": "⑧ローテ",
          "score": 5,
          "weight": 10,
          "items": [
            {
              "sign": "-",
              "label": "間隔 中18週"
            }
          ]
        }
      ]
    },
    {
      "number": 14,
      "name": "ミレヴィーナス",
      "gate": 7,
      "sex_age": "牝4",
      "weight_carried": 56.0,
      "jockey": "菅原明",
      "sire": "ヘニーヒューズ",
      "running_style": "逃",
      "scratched": false,
      "scores": {
        "s1": 6,
        "s2": 6,
        "s34": 8,
        "s5": 6,
        "s6": 7,
        "s7": 8,
        "s8": 6
      },
      "total": 65.0,
      "rank": 7,
      "estimated_prob": 0.036013,
      "fair_odds": 27.8,
      "odds": 22.5,
      "popularity": 5,
      "ev": -0.19,
      "ability_mark": null,
      "bet_mark": null,
      "landmine_reason": null,
      "finish": 4,
      "finish_text": null,
      "final_odds": 22.5,
      "last_3f": 36.6,
      "passing": "7-9",
      "role": null,
      "grade": "C+",
      "factors": [
        {
          "dim": "s1",
          "label": "①近走",
          "score": 6,
          "weight": 25,
          "items": [
            {
              "sign": "-",
              "label": "格下でのみ好走"
            },
            {
              "sign": "-",
              "label": "直近で内容悪化"
            }
          ]
        },
        {
          "dim": "s2",
          "label": "②展開",
          "score": 6,
          "weight": 20,
          "items": [
            {
              "sign": "+",
              "label": "好走時の脚: 粘込型"
            },
            {
              "sign": "+",
              "label": "逃げ型（主逃げ候補）"
            }
          ]
        },
        {
          "dim": "s34",
          "label": "③④条件適性",
          "score": 8,
          "weight": 20,
          "items": [
            {
              "sign": "+",
              "label": "コース・距離: match"
            },
            {
              "sign": "+",
              "label": "馬場: 同馬場好走2回"
            }
          ]
        },
        {
          "dim": "s5",
          "label": "⑤調教",
          "score": 6,
          "weight": 5,
          "items": [
            {
              "sign": "+",
              "label": "調教: 好気配(+0.5)"
            },
            {
              "sign": "+",
              "label": "馬体重: 好走帯438kg付近"
            }
          ]
        },
        {
          "dim": "s6",
          "label": "⑥枠斤騎",
          "score": 7,
          "weight": 15,
          "items": [
            {
              "sign": "-",
              "label": "枠順: 7枠 不利(勝5%複16%/219走)"
            },
            {
              "sign": "+",
              "label": "斤量: 同斤量以上で好走歴"
            },
            {
              "sign": "+",
              "label": "騎手: コース ratio1.63(勝13%複32%/46走)"
            }
          ]
        },
        {
          "dim": "s7",
          "label": "⑦血統",
          "score": 8,
          "weight": 5,
          "items": [
            {
              "sign": "+",
              "label": "複勝率31.5%(縮小後,基準24.6%,73走)"
            }
          ]
        },
        {
          "dim": "s8",
          "label": "⑧ローテ",
          "score": 6,
          "weight": 10,
          "items": [
            {
              "sign": "+",
              "label": "リスクなし"
            }
          ]
        }
      ]
    },
    {
      "number": 15,
      "name": "ナサ",
      "gate": 8,
      "sex_age": "牝5",
      "weight_carried": 56.0,
      "jockey": "吉田豊",
      "sire": "ロードカナロア",
      "running_style": "先",
      "scratched": false,
      "scores": {
        "s1": 5,
        "s2": 6,
        "s34": 9,
        "s5": 6,
        "s6": 6,
        "s7": 4,
        "s8": 6
      },
      "total": 63.8,
      "rank": 11,
      "estimated_prob": 0.013528,
      "fair_odds": 73.9,
      "odds": 127.5,
      "popularity": 14,
      "ev": 0.72,
      "ability_mark": null,
      "bet_mark": null,
      "landmine_reason": null,
      "finish": 11,
      "finish_text": null,
      "final_odds": 127.5,
      "last_3f": 35.9,
      "passing": "14-13",
      "role": null,
      "grade": "C+",
      "factors": [
        {
          "dim": "s1",
          "label": "①近走",
          "score": 5,
          "weight": 25,
          "items": [
            {
              "sign": "+",
              "label": "直近で内容改善"
            },
            {
              "sign": "-",
              "label": "格下でのみ好走"
            },
            {
              "sign": "-",
              "label": "同級で安定して凡走"
            }
          ]
        },
        {
          "dim": "s2",
          "label": "②展開",
          "score": 6,
          "weight": 20,
          "items": [
            {
              "sign": "+",
              "label": "好走時の脚: 先行押切型"
            },
            {
              "sign": "+",
              "label": "先行型（逃げ候補）"
            }
          ]
        },
        {
          "dim": "s34",
          "label": "③④条件適性",
          "score": 9,
          "weight": 20,
          "items": [
            {
              "sign": "+",
              "label": "コース・距離: match"
            },
            {
              "sign": "+",
              "label": "馬場: 同馬場好走5回"
            }
          ]
        },
        {
          "dim": "s5",
          "label": "⑤調教",
          "score": 6,
          "weight": 5,
          "items": [
            {
              "sign": "+",
              "label": "調教: 上積十分(+0.3)"
            }
          ]
        },
        {
          "dim": "s6",
          "label": "⑥枠斤騎",
          "score": 6,
          "weight": 15,
          "items": [
            {
              "sign": "+",
              "label": "枠順: 8枠 大幅有利(勝9%複26%/221走)"
            }
          ]
        },
        {
          "dim": "s7",
          "label": "⑦血統",
          "score": 4,
          "weight": 5,
          "items": [
            {
              "sign": "-",
              "label": "複勝率14.5%(縮小後,基準21.8%,56走)"
            }
          ]
        },
        {
          "dim": "s8",
          "label": "⑧ローテ",
          "score": 6,
          "weight": 10,
          "items": [
            {
              "sign": "+",
              "label": "リスクなし"
            }
          ]
        }
      ]
    },
    {
      "number": 16,
      "name": "ドンアミティエ",
      "gate": 8,
      "sex_age": "牡3",
      "weight_carried": 55.0,
      "jockey": "松若",
      "sire": "アジアエクスプレス",
      "running_style": "逃",
      "scratched": false,
      "scores": {
        "s1": 7,
        "s2": 6,
        "s34": 8,
        "s5": 6,
        "s6": 6,
        "s7": 7,
        "s8": 6
      },
      "total": 67.8,
      "rank": 4,
      "estimated_prob": 0.341639,
      "fair_odds": 2.9,
      "odds": 1.7,
      "popularity": 1,
      "ev": -0.42,
      "ability_mark": "△",
      "bet_mark": "地雷",
      "landmine_reason": "単勝1.7倍(1番人気)だが推定勝率34.2%・単勝EV-42%",
      "finish": 1,
      "finish_text": null,
      "final_odds": 1.7,
      "last_3f": 37.0,
      "passing": "2-2",
      "role": null,
      "grade": "B",
      "factors": [
        {
          "dim": "s1",
          "label": "①近走",
          "score": 7,
          "weight": 25,
          "items": [
            {
              "sign": "-",
              "label": "格下でのみ好走"
            }
          ]
        },
        {
          "dim": "s2",
          "label": "②展開",
          "score": 6,
          "weight": 20,
          "items": [
            {
              "sign": "+",
              "label": "好走時の脚: 粘込型"
            },
            {
              "sign": "+",
              "label": "逃げ・先行型（逃げ候補）"
            }
          ]
        },
        {
          "dim": "s34",
          "label": "③④条件適性",
          "score": 8,
          "weight": 20,
          "items": [
            {
              "sign": "+",
              "label": "コース・距離: match"
            },
            {
              "sign": "+",
              "label": "馬場: 同馬場好走3回"
            }
          ]
        },
        {
          "dim": "s5",
          "label": "⑤調教",
          "score": 6,
          "weight": 5,
          "items": [
            {
              "sign": "+",
              "label": "調教: rankA(+0.6)"
            },
            {
              "sign": "-",
              "label": "馬体重: 3走で-18kg減少傾向"
            }
          ]
        },
        {
          "dim": "s6",
          "label": "⑥枠斤騎",
          "score": 6,
          "weight": 15,
          "items": [
            {
              "sign": "+",
              "label": "枠順: 8枠 大幅有利(勝9%複26%/221走)"
            },
            {
              "sign": "+",
              "label": "斤量: 同斤量以上で好走歴"
            }
          ]
        },
        {
          "dim": "s7",
          "label": "⑦血統",
          "score": 7,
          "weight": 5,
          "items": [
            {
              "sign": "+",
              "label": "複勝率25.0%(縮小後,基準21.8%,42走)"
            }
          ]
        },
        {
          "dim": "s8",
          "label": "⑧ローテ",
          "score": 6,
          "weight": 10,
          "items": [
            {
              "sign": "+",
              "label": "リスクなし"
            }
          ]
        }
      ]
    }
  ],
  "bets": [],
  "sections": {
    "overview_md": "**コース:** 福島ダ1150m\n**馬場:** \n**頭数:** 16頭\n\n**脚質傾向（コースデータ）:**\n- 逃げ: 33%/54%/65%（95走）→ 有利\n- 先行: 14%/30%/46%（313走）→ 有利\n- 差し: 2%/6%/11%（509走）→ 不利\n- 追込: 0%/1%/3%（542走）→ 不利\n- 内外バイアス: 内枠やや有利（1枠1.32, 2枠0.67, 3枠1.05, 4枠1.14, 5枠0.81, 6枠0.85, 7枠0.83, 8枠1.33）\n\n### 逃げ候補・先行圧判定\n\n| 馬番 | 馬名 | 分類 | 先行率 |\n|---:|---|---|---:|\n| 4 | ハギノオーロ | 逃げ | 1.60 |\n| 6 | エコロアイ | 逃げ | 1.60 |\n| 14 | ミレヴィーナス | 逃げ | 1.60 |\n| 2 | ニシノラーナ | 逃げ | 1.40 |\n| 1 | スイートカルデア | 先行(逃げ候補) | 1.20 |\n| 16 | ドンアミティエ | 先行(逃げ候補) | 1.20 |\n| 9 | ブルースコード | 先行(番手) | 1.00 |\n| 10 | エナジーロッソ | 先行(番手) | 1.00 |\n| 13 | アルマセクメト | 先行(番手) | 0.80 |\n| 12 | ロードミッドナイト | 先行 | 0.60 |\n| 15 | ナサ | 先行(番手) | 0.60 |\n\n**先行圧指数** = 0.819 → 高い(0.36〜)"
  },
  "result": {
    "recorded_at": "2026-07-21T16:04:15",
    "pace": "H",
    "winning_style": null,
    "bias_actual": null,
    "top3": [
      {
        "finish": 1,
        "number": 16,
        "name": "ドンアミティエ",
        "popularity": 1,
        "odds": 1.7
      },
      {
        "finish": 2,
        "number": 6,
        "name": "エコロアイ",
        "popularity": 4,
        "odds": 15.0
      },
      {
        "finish": 3,
        "number": 12,
        "name": "ロードミッドナイト",
        "popularity": 2,
        "odds": 4.4
      }
    ],
    "payouts": {
      "tansho": {
        "combination": [
          16
        ],
        "payout": 170,
        "popularity": 1
      },
      "fukusho": [
        {
          "combination": [
            16
          ],
          "payout": 120
        },
        {
          "combination": [
            6
          ],
          "payout": 310
        },
        {
          "combination": [
            12
          ],
          "payout": 130
        }
      ],
      "wakuren": {
        "combination": [
          3,
          8
        ],
        "payout": 490
      },
      "umaren": {
        "combination": [
          6,
          16
        ],
        "payout": 1430
      },
      "wide": [
        {
          "combination": [
            6,
            16
          ],
          "payout": 620
        },
        {
          "combination": [
            12,
            16
          ],
          "payout": 240
        },
        {
          "combination": [
            6,
            12
          ],
          "payout": 1010
        }
      ],
      "umatan": {
        "combination": [
          16,
          6
        ],
        "payout": 1700
      },
      "sanrenpuku": {
        "combination": [
          6,
          12,
          16
        ],
        "payout": 1790
      },
      "sanrentan": {
        "combination": [
          16,
          6,
          12
        ],
        "payout": 5770
      }
    }
  },
  "verification": {
    "pace_match": true,
    "bias_match": null,
    "bias_note": null,
    "mark_finishes": {
      "△(3)": 10,
      "○(5)": 14,
      "▲(11)": 15,
      "◎(12)": 3,
      "△(16)": 1
    },
    "any_mark_in_top3": true,
    "landmine_result": {
      "6": {
        "finish": 2,
        "ok": false
      },
      "16": {
        "finish": 1,
        "ok": false
      }
    },
    "bets_hit": false,
    "bets_cost": 0,
    "bets_return": 0,
    "biggest_miss": null,
    "miss_cause": null,
    "summary": null
  }
}